[
  {
    "word": "existence",
    "derivatives": [
      "exist (v.)"
    ],
    "phrases": []
  },
  {
    "word": "ascribe",
    "derivatives": [],
    "phrases": []
  },
  {
    "word": "threshold",
    "derivatives": [],
    "phrases": []
  },
  {
    "word": "float",
    "derivatives": [],
    "phrases": []
  },
  {
    "word": "minority",
    "derivatives": [],
    "phrases": []
  },
  {
    "word": "axis",
    "derivatives": [],
    "phrases": []
  },
  {
    "word": "pole",
    "derivatives": [],
    "phrases": []
  },
  {
    "word": "preferable",
    "derivatives": [
      "prefer (v.)"
    ],
    "phrases": []
  },
  {
    "word": "reference",
    "derivatives": [
      "refer (v.)"
    ],
    "phrases": []
  },
  {
    "word": "spite",
    "derivatives": [],
    "phrases": []
  },
  {
    "word": "defendant",
    "derivatives": [],
    "phrases": []
  },
  {
    "word": "arrange",
    "derivatives": [
      "arrangement (n.)"
    ],
    "phrases": [
      "arrange a meeting",
      "arrange for"
    ]
  },
  {
    "word": "olive",
    "derivatives": [],
    "phrases": []
  },
  {
    "word": "coarse",
    "derivatives": [],
    "phrases": []
  },
  {
    "word": "exaggerate",
    "derivatives": [],
    "phrases": []
  },
  {
    "word": "streamline",
    "derivatives": [],
    "phrases": []
  },
  {
    "word": "imply",
    "derivatives": [
      "implication (n.)",
      "implied (adj.)"
    ],
    "phrases": [
      "imply that",
      "as the name implies"
    ]
  },
  {
    "word": "offset",
    "derivatives": [],
    "phrases": []
  },
  {
    "word": "commitment",
    "derivatives": [
      "commit (v.)"
    ],
    "phrases": []
  },
  {
    "word": "cavity",
    "derivatives": [],
    "phrases": []
  },
  {
    "word": "coward",
    "derivatives": [],
    "phrases": []
  },
  {
    "word": "fossil",
    "derivatives": [],
    "phrases": []
  },
  {
    "word": "poke",
    "derivatives": [],
    "phrases": []
  },
  {
    "word": "rejection",
    "derivatives": [
      "reject (v.)"
    ],
    "phrases": []
  },
  {
    "word": "fixture",
    "derivatives": [],
    "phrases": []
  },
  {
    "word": "manufacture",
    "derivatives": [
      "manufacturing (n.)",
      "manufacturer (n.)"
    ],
    "phrases": [
      "manufacture goods",
      "manufacturing industry"
    ]
  },
  {
    "word": "collision",
    "derivatives": [],
    "phrases": []
  },
  {
    "word": "sequence",
    "derivatives": [],
    "phrases": []
  },
  {
    "word": "recruit",
    "derivatives": [],
    "phrases": []
  },
  {
    "word": "provision",
    "derivatives": [
      "provide (v.)"
    ],
    "phrases": []
  },
  {
    "word": "calorie",
    "derivatives": [],
    "phrases": []
  },
  {
    "word": "slogan",
    "derivatives": [],
    "phrases": []
  },
  {
    "word": "invariably",
    "derivatives": [],
    "phrases": []
  },
  {
    "word": "commence",
    "derivatives": [],
    "phrases": []
  },
  {
    "word": "tract",
    "derivatives": [],
    "phrases": []
  },
  {
    "word": "configuration",
    "derivatives": [],
    "phrases": []
  },
  {
    "word": "mercury",
    "derivatives": [],
    "phrases": []
  },
  {
    "word": "frequent",
    "derivatives": [
      "frequency (n.)",
      "frequently (adv.)"
    ],
    "phrases": []
  },
  {
    "word": "chunk",
    "derivatives": [],
    "phrases": []
  },
  {
    "word": "interact",
    "derivatives": [
      "interaction (n.)",
      "interactive (adj.)"
    ],
    "phrases": [
      "interact with",
      "interact socially"
    ]
  },
  {
    "word": "commonplace",
    "derivatives": [],
    "phrases": []
  },
  {
    "word": "aggregate",
    "derivatives": [],
    "phrases": []
  },
  {
    "word": "seemingly",
    "derivatives": [],
    "phrases": []
  },
  {
    "word": "attendant",
    "derivatives": [
      "attend (v.)"
    ],
    "phrases": []
  },
  {
    "word": "array",
    "derivatives": [],
    "phrases": []
  },
  {
    "word": "parameter",
    "derivatives": [],
    "phrases": []
  },
  {
    "word": "extinct",
    "derivatives": [],
    "phrases": []
  },
  {
    "word": "discriminate",
    "derivatives": [],
    "phrases": []
  },
  {
    "word": "degrade",
    "derivatives": [],
    "phrases": []
  },
  {
    "word": "opaque",
    "derivatives": [],
    "phrases": []
  },
  {
    "word": "repay",
    "derivatives": [],
    "phrases": []
  },
  {
    "word": "monetary",
    "derivatives": [],
    "phrases": []
  },
  {
    "word": "grave",
    "derivatives": [],
    "phrases": []
  },
  {
    "word": "advantage",
    "derivatives": [],
    "phrases": []
  },
  {
    "word": "controversy",
    "derivatives": [],
    "phrases": []
  },
  {
    "word": "command",
    "derivatives": [],
    "phrases": []
  },
  {
    "word": "compulsory",
    "derivatives": [],
    "phrases": []
  },
  {
    "word": "performance",
    "derivatives": [
      "perform (v.)"
    ],
    "phrases": []
  },
  {
    "word": "serial",
    "derivatives": [],
    "phrases": []
  },
  {
    "word": "anticipate",
    "derivatives": [
      "anticipation (n.)"
    ],
    "phrases": [
      "anticipate needs",
      "anticipate problems"
    ]
  },
  {
    "word": "detach",
    "derivatives": [],
    "phrases": []
  },
  {
    "word": "slash",
    "derivatives": [],
    "phrases": []
  },
  {
    "word": "fabricate",
    "derivatives": [],
    "phrases": []
  },
  {
    "word": "comic",
    "derivatives": [],
    "phrases": []
  },
  {
    "word": "perfection",
    "derivatives": [],
    "phrases": []
  },
  {
    "word": "vague",
    "derivatives": [],
    "phrases": []
  },
  {
    "word": "pope",
    "derivatives": [],
    "phrases": []
  },
  {
    "word": "exception",
    "derivatives": [
      "except (v.)"
    ],
    "phrases": []
  },
  {
    "word": "ego",
    "derivatives": [],
    "phrases": []
  },
  {
    "word": "urge",
    "derivatives": [
      "urgent (adj.)",
      "urgency (n.)"
    ],
    "phrases": [
      "urge to do",
      "urge caution"
    ]
  },
  {
    "word": "spouse",
    "derivatives": [],
    "phrases": []
  },
  {
    "word": "score",
    "derivatives": [],
    "phrases": []
  },
  {
    "word": "isle",
    "derivatives": [],
    "phrases": []
  },
  {
    "word": "enclosure",
    "derivatives": [],
    "phrases": []
  },
  {
    "word": "graduate",
    "derivatives": [
      "graduation (n.)",
      "undergraduate (n.)"
    ],
    "phrases": []
  },
  {
    "word": "famine",
    "derivatives": [],
    "phrases": []
  },
  {
    "word": "quota",
    "derivatives": [],
    "phrases": []
  },
  {
    "word": "unanimous",
    "derivatives": [],
    "phrases": []
  },
  {
    "word": "scorn",
    "derivatives": [],
    "phrases": []
  },
  {
    "word": "thermal",
    "derivatives": [],
    "phrases": []
  },
  {
    "word": "sulfur",
    "derivatives": [],
    "phrases": []
  },
  {
    "word": "visual",
    "derivatives": [],
    "phrases": []
  },
  {
    "word": "terrain",
    "derivatives": [],
    "phrases": []
  },
  {
    "word": "grief",
    "derivatives": [],
    "phrases": []
  },
  {
    "word": "rap",
    "derivatives": [],
    "phrases": []
  },
  {
    "word": "upgrade",
    "derivatives": [],
    "phrases": []
  },
  {
    "word": "instruct",
    "derivatives": [
      "instruction (n.)"
    ],
    "phrases": []
  },
  {
    "word": "appendix",
    "derivatives": [],
    "phrases": []
  },
  {
    "word": "virtually",
    "derivatives": [],
    "phrases": []
  },
  {
    "word": "agreeable",
    "derivatives": [
      "agree (v.)"
    ],
    "phrases": []
  },
  {
    "word": "economy",
    "derivatives": [
      "economic (adj.)",
      "economical (adj.)"
    ],
    "phrases": []
  },
  {
    "word": "community",
    "derivatives": [],
    "phrases": []
  },
  {
    "word": "version",
    "derivatives": [],
    "phrases": []
  },
  {
    "word": "sprinkle",
    "derivatives": [],
    "phrases": []
  },
  {
    "word": "bronze",
    "derivatives": [],
    "phrases": []
  },
  {
    "word": "conception",
    "derivatives": [],
    "phrases": []
  },
  {
    "word": "municipal",
    "derivatives": [],
    "phrases": []
  },
  {
    "word": "detain",
    "derivatives": [],
    "phrases": []
  },
  {
    "word": "institute",
    "derivatives": [],
    "phrases": []
  },
  {
    "word": "endure",
    "derivatives": [],
    "phrases": []
  },
  {
    "word": "detail",
    "derivatives": [],
    "phrases": []
  },
  {
    "word": "subculture",
    "derivatives": [],
    "phrases": []
  },
  {
    "word": "appropriate",
    "derivatives": [],
    "phrases": []
  },
  {
    "word": "criterion",
    "derivatives": [],
    "phrases": []
  },
  {
    "word": "essence",
    "derivatives": [],
    "phrases": []
  },
  {
    "word": "pore",
    "derivatives": [],
    "phrases": []
  },
  {
    "word": "utility",
    "derivatives": [],
    "phrases": []
  },
  {
    "word": "manual",
    "derivatives": [],
    "phrases": []
  },
  {
    "word": "maneuver",
    "derivatives": [],
    "phrases": []
  },
  {
    "word": "symphony",
    "derivatives": [],
    "phrases": []
  },
  {
    "word": "eloquent",
    "derivatives": [],
    "phrases": []
  },
  {
    "word": "optimistic",
    "derivatives": [],
    "phrases": []
  },
  {
    "word": "dual",
    "derivatives": [],
    "phrases": []
  }
]